metaerrors/__init__.py
metaerrors/freebsd.py
metaerrors/linux.py
metaerrors/mac.py
metaerrors/tools.py
metaerrors/win.py
metaerrors-2.0.dist-info/licenses/LICENSE
metaerrors-2.0.dist-info/METADATA
metaerrors-2.0.dist-info/WHEEL
metaerrors-2.0.dist-info/top_level.txt
metaerrors-2.0.dist-info/RECORD
