Metadata-Version: 2.4
Name: metaerrors
Version: 2.0
Summary: Outputs exceptions in popups
Home-page: https://github.com/IgorNk500/metaerrors
Author: IgorNk500
License: MIT
Keywords: exceptions,errors,popup,pop-up,error,exception,popups,pop-ups,dialog,window,dialog window,dialog windows
Platform: Linux
Platform: Windows
Platform: macOS
Platform: FreeBSD
Classifier: Programming Language :: Python :: 3
Classifier: Development Status :: 5 - Production/Stable
Classifier: Natural Language :: English
Classifier: Operating System :: Microsoft :: Windows :: Windows 11
Classifier: Operating System :: Microsoft :: Windows :: Windows 10
Classifier: Operating System :: Microsoft :: Windows :: Windows 8.1
Classifier: Operating System :: Microsoft :: Windows :: Windows 8
Classifier: Operating System :: Microsoft :: Windows :: Windows 7
Classifier: Operating System :: MacOS
Classifier: Operating System :: POSIX :: BSD :: FreeBSD
Classifier: Operating System :: POSIX :: Linux
Classifier: Environment :: GPU
Requires-Python: >=3.8.0
License-File: LICENSE
Dynamic: author
Dynamic: classifier
Dynamic: description
Dynamic: description-content-type
Dynamic: home-page
Dynamic: keywords
Dynamic: license
Dynamic: license-file
Dynamic: platform
Dynamic: requires-python
Dynamic: summary
